sanatio/__init__.py
sanatio/array_validator.py
sanatio/base_class.py
sanatio/date_validator.py
sanatio/document_validator.py
sanatio/email_validator.py
sanatio/file_validator.py
sanatio/number_validator.py
sanatio/other_validator.py
sanatio/password_validator.py
sanatio/string_validator.py
sanatio/username_validator.py
sanatio/assets/country.json
sanatio/assets/regex.json
sanatio/utils/__init__.py
sanatio/utils/checksum.py
sanatio/utils/utils.py
sanatio-1.7.0.data/data/assets/country.json
sanatio-1.7.0.data/data/assets/regex.json
sanatio-1.7.0.dist-info/licenses/LICENSE
sanatio-1.7.0.dist-info/METADATA
sanatio-1.7.0.dist-info/WHEEL
sanatio-1.7.0.dist-info/top_level.txt
sanatio-1.7.0.dist-info/RECORD
