Metadata-Version: 2.4
Name: Sanatio
Version: 1.7.0
Summary: Simple and easy to validate data in Python
Home-page: https://github.com/codeperfectplus/Sanatio
Author: Deepak Raj
Author-email: deepak008@live.com
Project-URL: Documentation, https://sanatio.readthedocs.io/en/latest/
Project-URL: Source, https://github.com/codeperfectplus/Sanatio
Project-URL: Tracker, https://github.com/codeperfectplus/Sanatio/issues
Keywords: sanatio,validation,python,data,data-validation,data-validation-python,data-validation-library,data-validation-python-library,data-validation-python-package,data-validation-package,data-validation-library-python
Classifier: Development Status :: 5 - Production/Stable
Classifier: Programming Language :: Python :: 3
Classifier: License :: OSI Approved :: Apache Software License
Classifier: Operating System :: OS Independent
Classifier: Intended Audience :: Developers
Requires-Python: >=3.4
License-File: LICENSE
Requires-Dist: python-Levenshtein==0.25.1
Requires-Dist: python-dateutil
Requires-Dist: pytest
Requires-Dist: pytest-xdist
Dynamic: author
Dynamic: author-email
Dynamic: classifier
Dynamic: description
Dynamic: description-content-type
Dynamic: home-page
Dynamic: keywords
Dynamic: license-file
Dynamic: project-url
Dynamic: requires-dist
Dynamic: requires-python
Dynamic: summary
